CHANGES
LICENSE
MANIFEST.in
Makefile
README
setup.py
tox.ini
audiodiff/__init__.py
audiodiff/commandlinetool.py
audiodiff.egg-info/PKG-INFO
audiodiff.egg-info/SOURCES.txt
audiodiff.egg-info/dependency_links.txt
audiodiff.egg-info/entry_points.txt
audiodiff.egg-info/requires.txt
audiodiff.egg-info/top_level.txt
docs/.gitignore
docs/Makefile
docs/conf.py
docs/index.rst
docs/_build/doctrees/environment.pickle
docs/_build/doctrees/index.doctree
docs/_build/html/.buildinfo
docs/_build/html/genindex.html
docs/_build/html/index.html
docs/_build/html/objects.inv
docs/_build/html/py-modindex.html
docs/_build/html/search.html
docs/_build/html/searchindex.js
docs/_build/html/_modules/audiodiff.html
docs/_build/html/_modules/index.html
docs/_build/html/_modules/audiodiff/commandlinetool.html
docs/_build/html/_sources/index.txt
docs/_build/html/_static/ajax-loader.gif
docs/_build/html/_static/basic.css
docs/_build/html/_static/comment-bright.png
docs/_build/html/_static/comment-close.png
docs/_build/html/_static/comment.png
docs/_build/html/_static/default.css
docs/_build/html/_static/doctools.js
docs/_build/html/_static/down-pressed.png
docs/_build/html/_static/down.png
docs/_build/html/_static/file.png
docs/_build/html/_static/jquery.js
docs/_build/html/_static/minus.png
docs/_build/html/_static/plus.png
docs/_build/html/_static/pygments.css
docs/_build/html/_static/searchtools.js
docs/_build/html/_static/sidebar.js
docs/_build/html/_static/underscore.js
docs/_build/html/_static/up-pressed.png
docs/_build/html/_static/up.png
docs/_build/html/_static/websupport.js
docs/_build/html/_static/css/badge_only.css
docs/_build/html/_static/css/theme.css
docs/_build/html/_static/font/fontawesome_webfont.eot
docs/_build/html/_static/font/fontawesome_webfont.svg
docs/_build/html/_static/font/fontawesome_webfont.ttf
docs/_build/html/_static/font/fontawesome_webfont.woff
docs/_build/html/_static/js/theme.js
tests/.DS_Store
tests/__init__.py
tests/test_audiodiff.py
tests/files/.coverage
tests/files/mahler.flac
tests/files/mahler.m4a
tests/files/mahler.mp3
tests/files/mahler.wav
tests/files/mahler_tagsdiff.m4a
tests/files/unicode.flac
tests/files/x/animal
tests/files/x/ä.flac
