Metadata-Version: 1.1
Name: audiodiff
Version: 0.3.0
Summary: Small library for comparing audio files
Home-page: https://github.com/clee704/audiodiff
Author: Choongmin Lee
Author-email: choongmin@me.com
License: MIT
Keywords: lossless audio metadata comparison
Platform: UNKNOWN
Classifier: Development Status :: 3 - Alpha
Classifier: Intended Audience :: Developers
Classifier: Intended Audience :: End Users/Desktop
Classifier: License :: OSI Approved :: MIT License
Classifier: Programming Language :: Python :: 2.6
Classifier: Programming Language :: Python :: 2.7
Classifier: Programming Language :: Python :: Implementation :: CPython
Classifier: Topic :: Multimedia :: Sound/Audio :: Analysis
Classifier: Topic :: Utilities
